user_agent2/__init__.py
user_agent2/base.py
user_agent2/util.py
user_agent2-2021.12.11.dist-info/LICENSE
user_agent2-2021.12.11.dist-info/METADATA
user_agent2-2021.12.11.dist-info/WHEEL
user_agent2-2021.12.11.dist-info/top_level.txt
user_agent2-2021.12.11.dist-info/RECORD
