Metadata-Version: 2.1
Name: user-agent2
Version: 2021.12.11
Summary: generate random user agent
Home-page: https://github.com/dytttf/user_agent2
Author: Dytttf
Author-email: dytttf@foxmail.com
License: BSD
Keywords: user_agent
Platform: UNKNOWN
License-File: LICENSE
Requires-Dist: user-agent (==0.1.10)
